new_dale_chall_readability/__init__.py
new_dale_chall_readability/easy_words.py
new_dale_chall_readability/formulas.py
new_dale_chall_readability/utils.py
new_dale_chall_readability-1.0.13.dist-info/LICENSE
new_dale_chall_readability-1.0.13.dist-info/METADATA
new_dale_chall_readability-1.0.13.dist-info/WHEEL
new_dale_chall_readability-1.0.13.dist-info/RECORD
