Metadata-Version: 2.1
Name: new-dale-chall-readability
Version: 1.0.13
Summary: Implements the New Dale-Chall readability formula. Its output is tested against samples from the original publication.
Home-page: https://github.com/public-law/readability
License: MIT
Keywords: nlp,readability,dale-chall
Author: Robb Shecter
Author-email: robb@public.law
Requires-Python: >=3.10,<4.0
Classifier: Development Status :: 5 - Production/Stable
Classifier: Intended Audience :: Developers
Classifier: License :: OSI Approved :: MIT License
Classifier: Natural Language :: English
Classifier: Operating System :: OS Independent
Classifier: Programming Language :: Python :: 3
Classifier: Programming Language :: Python :: 3.10
Classifier: Programming Language :: Python :: 3.11
Classifier: Programming Language :: Python :: 3.12
Classifier: Programming Language :: Python :: 3.13
Classifier: Topic :: Text Processing :: Linguistic
Classifier: Typing :: Typed
Requires-Dist: beautifulsoup4
Project-URL: Repository, https://github.com/public-law/readability
